xformula/__init__.py
xformula/__version__.py
xformula/arch/__init__.py
xformula/arch/bisect/__init__.py
xformula/arch/bisect/bisect.py
xformula/arch/enumeration/__init__.py
xformula/arch/enumeration/iota.py
xformula/arch/enumeration/zip.py
xformula/arch/meta/__init__.py
xformula/arch/meta/configurable.py
xformula/arch/meta/meta.py
xformula/arch/meta/options.py
xformula/arch/runtime/__init__.py
xformula/arch/runtime/reflection/__init__.py
xformula/arch/runtime/reflection/class_builder.py
xformula/py.typed
xformula/runtime/__init__.py
xformula/runtime/core/__init__.py
xformula/runtime/core/context/__init__.py
xformula/runtime/core/context/abc/__init__.py
xformula/runtime/core/context/abc/runtime_context.py
xformula/syntax/__init__.py
xformula/syntax/ast/__init__.py
xformula/syntax/ast/nodes/__init__.py
xformula/syntax/ast/nodes/abc/__init__.py
xformula/syntax/ast/nodes/abc/arity.py
xformula/syntax/ast/nodes/abc/associativity.py
xformula/syntax/ast/nodes/abc/attribute.py
xformula/syntax/ast/nodes/abc/call.py
xformula/syntax/ast/nodes/abc/container.py
xformula/syntax/ast/nodes/abc/context.py
xformula/syntax/ast/nodes/abc/dict.py
xformula/syntax/ast/nodes/abc/expression.py
xformula/syntax/ast/nodes/abc/has_arguments.py
xformula/syntax/ast/nodes/abc/has_arity.py
xformula/syntax/ast/nodes/abc/has_associativity.py
xformula/syntax/ast/nodes/abc/has_callee.py
xformula/syntax/ast/nodes/abc/has_context.py
xformula/syntax/ast/nodes/abc/has_elements.py
xformula/syntax/ast/nodes/abc/has_name.py
xformula/syntax/ast/nodes/abc/has_operands.py
xformula/syntax/ast/nodes/abc/has_operator.py
xformula/syntax/ast/nodes/abc/has_owner.py
xformula/syntax/ast/nodes/abc/has_placement.py
xformula/syntax/ast/nodes/abc/has_precedence_level.py
xformula/syntax/ast/nodes/abc/has_symbols.py
xformula/syntax/ast/nodes/abc/has_type.py
xformula/syntax/ast/nodes/abc/has_value.py
xformula/syntax/ast/nodes/abc/identifier.py
xformula/syntax/ast/nodes/abc/list.py
xformula/syntax/ast/nodes/abc/literal.py
xformula-0.1.1.dist-info/LICENSE
xformula-0.1.1.dist-info/WHEEL
xformula-0.1.1.dist-info/METADATA
xformula-0.1.1.dist-info/RECORD
