Metadata-Version: 2.1
Name: xformula
Version: 0.1.1
Summary: Highly customizable language front-end, aimed to be a base for custom DSL evaluators.
License: MIT
Author: Ertuğrul Keremoğlu
Author-email: ertugkeremoglu@gmail.com
Requires-Python: >=3.11,<4.0
Classifier: License :: OSI Approved :: MIT License
Classifier: Programming Language :: Python :: 3
Classifier: Programming Language :: Python :: 3.11
Requires-Dist: lark (>=1.1.4)
